[
  {
    "id": 1,
    "name": "mirai_koyomi",
    "icon": "c02UkKn1_400x400.jpg",
    "twitter": "mirai_koyomi_",
    "pixiv": "16229342",
    "bio": "なんたらかんたらうんたらかんたらたんたたんたんたんたんたん"
  },
  {
    "id": 2,
    "name": "コヨミ＝ダニエル＝ミライ",
    "icon": "c02UkKn1_400x400.jpg",
    "twitter": "mirai_koyomi_",
    "bio": "ごっつええ思案。\n\nいろいろあってPixivでの公開止めてます。Twitterの方にも掲載しているので、そちらからどうぞ。\nその後の掲載先は後々考えます。たぶん。"
  },
  {
    "id": 3,
    "name": "ダイアモンド☆コヨミ",
    "icon": "c02UkKn1_400x400.jpg",
    "pixiv": "16229342",
    "bio": "なんたらかんたらうんたらかんたらたんたたんたんたんたんたん"
  },
  {
    "id": 4,
    "name": "ゼンタ・シアンマッ!!",
    "icon": "c02UkKn1_400x400.jpg",
    "pixiv": "16229342",
    "bio": "なんたらかんたらうんたらかんたらたんたたんたんたんたんたん"
  },
  {
    "id": 5,
    "name": "Cyan The Mangenta",
    "icon": "c02UkKn1_400x400.jpg",
    "twitter": "mirai_koyomi_",
    "pixiv": "16229342",
    "bio": "ごっつええ思案。\n\nいろいろあってPixivでの公開止めてます。Twitterの方にも掲載しているので、そちらからどうぞ。\nその後の掲載先は後々考えます。たぶん。"
  },
  {
    "id": 6,
    "name": "桧",
    "icon": "c02UkKn1_400x400.jpg",
    "twitter": "hinoki_c",
    "bio": "ヒノキと読みます。木です。ヘブバン用垢。krtkとmnstを推しています。3章クリア済み。現在4章day12。20↑"
  },
  {
    "id": 7,
    "name": "こうた",
    "icon": "FjSc4TI2_400x400.jpg",
    "twitter": "kesigomutopen",
    "bio": "朝６時から月蔵布教LINEをもらい、深夜0時に月蔵合同参加通話した、こうたと申します。\nお友達が元気で嬉しいね。\n漫画描くの、楽しかったです。お誘いいただき、ありがとうございました。\n月蔵が幸せで嬉しいね。"
  }
]
